./.gitignore
./PKG-INFO
./README.md
./pyproject.toml
./vision_agents/plugins/pocket/__init__.py
./vision_agents/plugins/pocket/tts.py
vision_agents/plugins/pocket/__init__.py
vision_agents/plugins/pocket/tts.py
vision_agents_plugins_pocket-0.2.10.dist-info/METADATA
vision_agents_plugins_pocket-0.2.10.dist-info/WHEEL
vision_agents_plugins_pocket-0.2.10.dist-info/RECORD
