Metadata-Version: 2.4
Name: vision-agents-plugins-pocket
Version: 0.2.10
Summary: Pocket TTS integration for Vision Agents - lightweight CPU-based text-to-speech
Project-URL: Documentation, https://visionagents.ai/
Project-URL: Website, https://visionagents.ai/
Project-URL: Source, https://github.com/GetStream/Vision-Agents
License-Expression: MIT
Keywords: AI,TTS,agents,kyutai,pocket-tts,text-to-speech,voice agents
Requires-Python: >=3.10
Requires-Dist: pocket-tts>=0.1.0
Requires-Dist: vision-agents
